setup.py
dsnd_probability_6212019/Binomialdistribution.py
dsnd_probability_6212019/Gaussiandistribution.py
dsnd_probability_6212019/Generaldistribution.py
dsnd_probability_6212019/__init__.py
dsnd_probability_6212019.egg-info/PKG-INFO
dsnd_probability_6212019.egg-info/SOURCES.txt
dsnd_probability_6212019.egg-info/dependency_links.txt
dsnd_probability_6212019.egg-info/not-zip-safe
dsnd_probability_6212019.egg-info/top_level.txt